sirataxi
